pyhf_combine_converter/__init__.py
pyhf_combine_converter/combine_to_pyhf.py
pyhf_combine_converter/pyhf_to_combine.py
pyhf_combine_converter/version.py
pyhf_combine_converter-0.0.5.dist-info/METADATA
pyhf_combine_converter-0.0.5.dist-info/WHEEL
pyhf_combine_converter-0.0.5.dist-info/entry_points.txt
pyhf_combine_converter-0.0.5.dist-info/licenses/LICENSE.txt
pyhf_combine_converter-0.0.5.dist-info/RECORD
