Metadata-Version: 2.1
Name: pyhf_combine_converter
Version: 0.0.5
Summary: A package to translate between pyhf and Combine models
Project-URL: Homepage, https://github.com/peterridolfi/Pyhf-to-Combine-converter
Project-URL: Bug Tracker, https://github.com/peterridolfi/Pyhf-to-Combine-converter/issues
Author-email: Peter Ridolfi <petey.ridolfi7@gmail.com>
License-File: LICENSE.txt
Classifier: License :: OSI Approved :: MIT License
Classifier: Operating System :: OS Independent
Classifier: Programming Language :: Python :: 3
Requires-Python: >=3.7
Requires-Dist: hist>=2.6.1
Requires-Dist: pyhf>=0.6.3
Requires-Dist: uproot>=4.2.3
